neighbors/__init__.py
neighbors/_fit.py
neighbors/base.py
neighbors/data.py
neighbors/models.py
neighbors/utils.py
neighbors/version.py
neighbors/data/movielens100k.csv
neighbors/tests/__init__.py
neighbors/tests/conftest.py
neighbors/tests/test_data.py
neighbors/tests/test_models.py
neighbors/tests/test_utils.py
neighbors-0.1.0.dist-info/LICENSE
neighbors-0.1.0.dist-info/METADATA
neighbors-0.1.0.dist-info/WHEEL
neighbors-0.1.0.dist-info/top_level.txt
neighbors-0.1.0.dist-info/RECORD
